audio_validator/__init__.py
audio_validator/validator.py
django_audio_validator-0.0.3.dist-info/LICENSE
django_audio_validator-0.0.3.dist-info/METADATA
django_audio_validator-0.0.3.dist-info/WHEEL
django_audio_validator-0.0.3.dist-info/top_level.txt
django_audio_validator-0.0.3.dist-info/RECORD
