Metadata-Version: 2.1
Name: django-audio-validator
Version: 0.0.3
Summary: a packages for validate audio file in django
Home-page: https://github.com/rzashakeri/django-audio-validator
Author: Reza Shakeri
Author-email: rzashakeri@outlook.com
Project-URL: Bug Tracker, https://github.com/rzashakeri/django-audio-validator/issues
Classifier: Programming Language :: Python :: 3
Classifier: License :: OSI Approved :: MIT License
Classifier: Operating System :: OS Independent
Classifier: Framework :: Django
Requires-Python: >=3.6
License-File: LICENSE
Requires-Dist: filetype
